kirami_plugin_beauty_rate-0.1.2.dist-info/METADATA
kirami_plugin_beauty_rate-0.1.2.dist-info/WHEEL
kirami_plugin_beauty_rate-0.1.2.dist-info/licenses/LICENSE
kirami_plugin_beauty_rate/__init__.py
kirami_plugin_beauty_rate/config.py
kirami_plugin_beauty_rate/service.toml
kirami_plugin_beauty_rate/utils.py
kirami_plugin_beauty_rate-0.1.2.dist-info/RECORD
