Metadata-Version: 2.1
Name: kirami-plugin-beauty-rate
Version: 0.1.2
Summary: 基于 KiramiBot 的颜值评分插件
Author-Email: Komorebi <mute231010@gmail.com>
License: MIT
Project-URL: Homepage, https://github.com/KomoriDev/kirami-plugin-beauty-rate
Project-URL: Repository, https://github.com/KomoriDev/kirami-plugin-beauty-rate
Requires-Python: >=3.10
Requires-Dist: kiramibot>=0.3.2
Requires-Dist: nonebot-plugin-alconna>=0.25.1
